kedro_kubeflow/__init__.py
kedro_kubeflow/auth.py
kedro_kubeflow/cli.py
kedro_kubeflow/config.py
kedro_kubeflow/context_helper.py
kedro_kubeflow/generators/__init__.py
kedro_kubeflow/generators/one_pod_pipeline_generator.py
kedro_kubeflow/generators/pod_per_node_pipeline_generator.py
kedro_kubeflow/generators/utils.py
kedro_kubeflow/hooks.py
kedro_kubeflow/kfpclient.py
kedro_kubeflow/templates/github-on-merge-to-master.yml
kedro_kubeflow/templates/github-on-push.yml
kedro_kubeflow/utils.py
kedro_kubeflow-0.9.0.dist-info/LICENSE
kedro_kubeflow-0.9.0.dist-info/METADATA
kedro_kubeflow-0.9.0.dist-info/WHEEL
kedro_kubeflow-0.9.0.dist-info/entry_points.txt
kedro_kubeflow-0.9.0.dist-info/RECORD
