Metadata-Version: 2.3
Name: kedro-kubeflow
Version: 0.9.0
Summary: Kedro plugin with Kubeflow Pipelines support
License: Apache-2.0
Keywords: kedro-plugin,kubeflow,machinelearning,mlops,kubeflow-pipelines,kedro
Author: Mateusz Pytel
Author-email: mateusz.pytel@getindata.com
Maintainer: GetInData MLOPS
Maintainer-email: mlops@getindata.com
Requires-Python: >=3.8,<3.12
Classifier: Development Status :: 4 - Beta
Classifier: License :: OSI Approved :: Apache Software License
Classifier: Programming Language :: Python :: 3
Classifier: Programming Language :: Python :: 3.8
Classifier: Programming Language :: Python :: 3.9
Classifier: Programming Language :: Python :: 3.10
Classifier: Programming Language :: Python :: 3.11
Provides-Extra: gcp
Provides-Extra: mlflow
Requires-Dist: click (>=8.0.4)
Requires-Dist: fsspec (>=2021.4)
Requires-Dist: gcsfs (>=2021.4) ; extra == "gcp"
Requires-Dist: google-auth (<3) ; extra == "gcp"
Requires-Dist: kedro (>0.18.4,<=0.19.8)
Requires-Dist: kedro-mlflow (>=0.11.0) ; extra == "mlflow"
Requires-Dist: kfp (>=1.8.12,<2.0)
Requires-Dist: pyyaml (>=6.0,<7.0)
Requires-Dist: semver (>=2.10,<3.0)
Requires-Dist: tabulate (>=0.8.7)
Project-URL: Documentation, https://kedro-kubeflow.readthedocs.io/
Project-URL: Homepage, https://github.com/getindata/kedro-kubeflow
Project-URL: Repository, https://github.com/getindata/kedro-kubeflow
